{
    "Comment": "Generate Registration Token and Send Email and SMS parallely",
    "StartAt": "Generate Token",
    "States": {
      "Generate Token": {
        "Type": "Task",
        "Resource": "arn:aws:lambda:<REGION>:<ACCOUNT_ID>:function:state-1-generate-token",
        "InputPath": "$.user",
        "ResultPath": "$.user.tokenDetails",
        "Next": "Choice State"
      },
      "Choice State": {
        "Type" : "Choice",
        "Choices": [
          {
            "Variable": "$.user.tokenDetails.status",
            "BooleanEquals": true,
            "Next": "Parallel State"
          },
          {
            "Variable": "$.user.tokenDetails.status",
            "BooleanEquals": false,
            "Next": "End"
          }
        ]
      },
      "Parallel State": {
       "Type": "Parallel",
        "Next": "End",
        "Branches": [
          {
            "StartAt": "Send Email",
            "States": {
              "Send Email":{
                "Type": "Task",
                "Resource": "arn:aws:lambda:<REGION>:<ACCOUNT_ID>:function:p-state-1-sendTokenEmail",
                "InputPath": "$.user",
                "ResultPath": "$.user.emailDetails",
                "End": true
              }
            }
          },
          {
          "StartAt": "Send SMS",
          "States": {
            "Send SMS":{
              "Type": "Task",
              "Resource": "arn:aws:lambda:<REGION>:<ACCOUNT_ID>:function:p-state-2-sendTokenSMS",
              "InputPath": "$.user",
              "ResultPath": "$.user.smsDetails",
              "End": true
            }
          }
          }
        ]
      },
      "End": {
        "Type": "Succeed"
      }
    }
  }